[
    {
        "team_id": 36,
        "team_name": "Manchester City",
        "lineup": [
            {
                "player_id": 3067,
                "player_name": "Ederson Santana de Moraes",
                "player_nickname": "Ederson Moraes",
                "birth_date": "1993-08-17",
                "player_gender": "male",
                "player_height": 188.0,
                "player_weight": 86.0,
                "jersey_number": 31,
                "country": {
                    "id": 31,
                    "name": "Brazil"
                },
                "positions": [
                    {
                        "position_id": 1,
                        "position": "Goalkeeper",
                        "from": "00:00:00.000",
                        "to": null,
                        "from_period": 1,
                        "to_period": null,
                        "start_reason": "Starting XI",
                        "end_reason": "Final Whistle"
                    }
                ],
                "stats": {
                    "own_goals": 0,
                    "goals": 0,
                    "assists": 0,
                    "penalties_scored": 0,
                    "penalties_missed": 0,
                    "penalties_saved": 0
                }
            },
            {
                "player_id": 3193,
                "player_name": "Bernardo Mota Veiga de Carvalho e Silva",
                "player_nickname": "Bernardo Silva",
                "birth_date": "1994-08-10",
                "player_gender": "male",
                "player_height": 173.0,
                "player_weight": 64.0,
                "jersey_number": 20,
                "country": {
                    "id": 183,
                    "name": "Portugal"
                },
                "positions": [
                    {
                        "position_id": 18,
                        "position": "Right Attacking Midfield",
                        "from": "00:00:00.000",
                        "to": "01:24:35.047",
                        "from_period": 1,
                        "to_period": 2,
                        "start_reason": "Starting XI",
                        "end_reason": "Substitution - Off (Tactical)",
                        "counterpart_id": 104825,
                        "counterpart_name": "Oscar Bobb"
                    }
                ],
                "stats": {
                    "own_goals": 0,
                    "goals": 2,
                    "assists": 0,
                    "penalties_scored": 0,
                    "penalties_missed": 0,
                    "penalties_saved": 0
                }
            },
            {
                "player_id": 3205,
                "player_name": "Kyle Walker",
                "player_nickname": null,
                "birth_date": "1990-05-28",
                "player_gender": "male",
                "player_height": 178.0,
                "player_weight": 80.0,
                "jersey_number": 2,
                "country": {
                    "id": 68,
                    "name": "England"
                },
                "positions": [
                    {
                        "position_id": 7,
                        "position": "Right Wing Back",
                        "from": "00:00:00.000",
                        "to": "01:10:13.881",
                        "from_period": 1,
                        "to_period": 2,
                        "start_reason": "Starting XI",
                        "end_reason": "Tactical Shift"
                    },
                    {
                        "position_id": 3,
                        "position": "Right Center Back",
                        "from": "01:10:13.881",
                        "to": null,
                        "from_period": 2,
                        "to_period": null,
                        "start_reason": "Tactical Shift",
                        "end_reason": "Final Whistle"
                    }
                ],
                "stats": {
                    "own_goals": 0,
                    "goals": 0,
                    "assists": 0,
                    "penalties_scored": 0,
                    "penalties_missed": 0,
                    "penalties_saved": 0
                }
            },
            {
                "player_id": 3244,
                "player_name": "John Stones",
                "player_nickname": null,
                "birth_date": "1994-05-28",
                "player_gender": "male",
                "player_height": 188.0,
                "player_weight": 80.0,
                "jersey_number": 5,
                "country": {
                    "id": 68,
                    "name": "England"
                },
                "positions": [
                    {
                        "position_id": 4,
                        "position": "Center Back",
                        "from": "00:00:00.000",
                        "to": "01:10:11.268",
                        "from_period": 1,
                        "to_period": 2,
                        "start_reason": "Starting XI",
                        "end_reason": "Substitution - Off (Tactical)",
                        "counterpart_id": 48705,
                        "counterpart_name": "Rico Lewis"
                    }
                ],
                "stats": {
                    "own_goals": 0,
                    "goals": 0,
                    "assists": 0,
                    "penalties_scored": 0,
                    "penalties_missed": 0,
                    "penalties_saved": 0
                }
            },
            {
                "player_id": 3306,
                "player_name": "Nathan Ak\u00e9",
                "player_nickname": null,
                "birth_date": "1995-02-18",
                "player_gender": "male",
                "player_height": 180.0,
                "player_weight": 75.0,
                "jersey_number": 6,
                "country": {
                    "id": 160,
                    "name": "Netherlands"
                },
                "positions": [
                    {
                        "position_id": 5,
                        "position": "Left Center Back",
                        "from": "00:00:00.000",
                        "to": null,
                        "from_period": 1,
                        "to_period": null,
                        "start_reason": "Starting XI",
                        "end_reason": "Final Whistle"
                    }
                ],
                "stats": {
                    "own_goals": 0,
                    "goals": 1,
                    "assists": 0,
                    "penalties_scored": 0,
                    "penalties_missed": 0,
                    "penalties_saved": 0
                }
            },
            {
                "player_id": 4354,
                "player_name": "Phil Foden",
                "player_nickname": null,
                "birth_date": "2000-05-28",
                "player_gender": "male",
                "player_height": 171.0,
                "player_weight": 70.0,
                "jersey_number": 47,
                "country": {
                    "id": 68,
                    "name": "England"
                },
                "positions": [
                    {
                        "position_id": 20,
                        "position": "Left Attacking Midfield",
                        "from": "00:45:00.000",
                        "to": "01:10:13.881",
                        "from_period": 2,
                        "to_period": 2,
                        "start_reason": "Substitution - On (Tactical)",
                        "end_reason": "Tactical Shift",
                        "counterpart_id": 23616,
                        "counterpart_name": "Erling H\u00e5land"
                    },
                    {
                        "position_id": 23,
                        "position": "Center Forward",
                        "from": "01:10:13.881",
                        "to": "01:24:36.000",
                        "from_period": 2,
                        "to_period": 2,
                        "start_reason": "Tactical Shift",
                        "end_reason": "Tactical Shift"
                    },
                    {
                        "position_id": 18,
                        "position": "Right Attacking Midfield",
                        "from": "01:24:36.000",
                        "to": null,
                        "from_period": 2,
                        "to_period": null,
                        "start_reason": "Tactical Shift",
                        "end_reason": "Final Whistle"
                    }
                ],
                "stats": {
                    "own_goals": 0,
                    "goals": 1,
                    "assists": 0,
                    "penalties_scored": 0,
                    "penalties_missed": 0,
                    "penalties_saved": 0
                }
            },
            {
                "player_id": 4706,
                "player_name": "Kalvin Phillips",
                "player_nickname": null,
                "birth_date": "1995-12-02",
                "player_gender": "male",
                "player_height": 178.0,
                "player_weight": 72.0,
                "jersey_number": 4,
                "country": {
                    "id": 68,
                    "name": "England"
                },
                "positions": [
                    {
                        "position_id": 9,
                        "position": "Right Defensive Midfield",
                        "from": "01:10:13.307",
                        "to": null,
                        "from_period": 2,
                        "to_period": null,
                        "start_reason": "Substitution - On (Tactical)",
                        "end_reason": "Final Whistle",
                        "counterpart_id": 6765,
                        "counterpart_name": "Rodrigo Hern\u00e1ndez Cascante"
                    }
                ],
                "stats": {
                    "own_goals": 0,
                    "goals": 0,
                    "assists": 0,
                    "penalties_scored": 0,
                    "penalties_missed": 0,
                    "penalties_saved": 0
                }
            },
            {
                "player_id": 5206,
                "player_name": "R\u00faben Santos Gato Alves Dias",
                "player_nickname": "R\u00faben Dias",
                "birth_date": "1997-05-14",
                "player_gender": "male",
                "player_height": 186.0,
                "player_weight": 76.0,
                "jersey_number": 3,
                "country": {
                    "id": 183,
                    "name": "Portugal"
                },
                "positions": [],
                "stats": []
            },
            {
                "player_id": 5456,
                "player_name": "Mateo Kova\u010di\u0107",
                "player_nickname": null,
                "birth_date": "1994-05-06",
                "player_gender": "male",
                "player_height": 178.0,
                "player_weight": 78.0,
                "jersey_number": 8,
                "country": {
                    "id": 56,
                    "name": "Croatia"
                },
                "positions": [
                    {
                        "position_id": 11,
                        "position": "Left Defensive Midfield",
                        "from": "00:00:00.000",
                        "to": null,
                        "from_period": 1,
                        "to_period": null,
                        "start_reason": "Starting XI",
                        "end_reason": "Final Whistle"
                    }
                ],
                "stats": {
                    "own_goals": 0,
                    "goals": 0,
                    "assists": 0,
                    "penalties_scored": 0,
                    "penalties_missed": 0,
                    "penalties_saved": 0
                }
            },
            {
                "player_id": 5549,
                "player_name": "Manuel Obafemi Akanji",
                "player_nickname": "Manuel Akanji",
                "birth_date": "1995-07-19",
                "player_gender": "male",
                "player_height": 187.0,
                "player_weight": 91.0,
                "jersey_number": 25,
                "country": {
                    "id": 221,
                    "name": "Switzerland"
                },
                "positions": [
                    {
                        "position_id": 3,
                        "position": "Right Center Back",
                        "from": "00:00:00.000",
                        "to": "01:10:13.881",
                        "from_period": 1,
                        "to_period": 2,
                        "start_reason": "Starting XI",
                        "end_reason": "Tactical Shift"
                    },
                    {
                        "position_id": 4,
                        "position": "Center Back",
                        "from": "01:10:13.881",
                        "to": null,
                        "from_period": 2,
                        "to_period": null,
                        "start_reason": "Tactical Shift",
                        "end_reason": "Final Whistle"
                    }
                ],
                "stats": {
                    "own_goals": 0,
                    "goals": 1,
                    "assists": 0,
                    "penalties_scored": 0,
                    "penalties_missed": 0,
                    "penalties_saved": 0
                }
            },
            {
                "player_id": 6765,
                "player_name": "Rodrigo Hern\u00e1ndez Cascante",
                "player_nickname": "Rodri",
                "birth_date": "1996-06-22",
                "player_gender": "male",
                "player_height": 191.0,
                "player_weight": 82.0,
                "jersey_number": 16,
                "country": {
                    "id": 214,
                    "name": "Spain"
                },
                "positions": [
                    {
                        "position_id": 9,
                        "position": "Right Defensive Midfield",
                        "from": "00:00:00.000",
                        "to": "01:10:13.307",
                        "from_period": 1,
                        "to_period": 2,
                        "start_reason": "Starting XI",
                        "end_reason": "Substitution - Off (Tactical)",
                        "counterpart_id": 4706,
                        "counterpart_name": "Kalvin Phillips"
                    }
                ],
                "stats": {
                    "own_goals": 0,
                    "goals": 0,
                    "assists": 1,
                    "penalties_scored": 0,
                    "penalties_missed": 0,
                    "penalties_saved": 0
                }
            },
            {
                "player_id": 9194,
                "player_name": "Stefan Ortega Moreno",
                "player_nickname": "Stefan Ortega",
                "birth_date": "1992-11-06",
                "player_gender": "male",
                "player_height": 185.0,
                "player_weight": 88.0,
                "jersey_number": 18,
                "country": {
                    "id": 85,
                    "name": "Germany"
                },
                "positions": [],
                "stats": []
            },
            {
                "player_id": 9638,
                "player_name": "Jack Grealish",
                "player_nickname": null,
                "birth_date": "1995-09-10",
                "player_gender": "male",
                "player_height": 175.0,
                "player_weight": 76.0,
                "jersey_number": 10,
                "country": {
                    "id": 68,
                    "name": "England"
                },
                "positions": [],
                "stats": []
            },
            {
                "player_id": 23616,
                "player_name": "Erling H\u00e5land",
                "player_nickname": "Erling Haaland",
                "birth_date": "2000-07-21",
                "player_gender": "male",
                "player_height": 194.0,
                "player_weight": 88.0,
                "jersey_number": 9,
                "country": {
                    "id": 171,
                    "name": "Norway"
                },
                "positions": [
                    {
                        "position_id": 23,
                        "position": "Center Forward",
                        "from": "00:00:00.000",
                        "to": "00:45:00.000",
                        "from_period": 1,
                        "to_period": 2,
                        "start_reason": "Starting XI",
                        "end_reason": "Substitution - Off (Tactical)",
                        "counterpart_id": 4354,
                        "counterpart_name": "Phil Foden"
                    }
                ],
                "stats": {
                    "own_goals": 0,
                    "goals": 0,
                    "assists": 0,
                    "penalties_scored": 0,
                    "penalties_missed": 0,
                    "penalties_saved": 0
                }
            },
            {
                "player_id": 23650,
                "player_name": "Jeremy Doku",
                "player_nickname": "J\u00e9r\u00e9my Doku",
                "birth_date": "2002-05-27",
                "player_gender": "male",
                "player_height": 171.0,
                "player_weight": 66.0,
                "jersey_number": 11,
                "country": {
                    "id": 22,
                    "name": "Belgium"
                },
                "positions": [
                    {
                        "position_id": 8,
                        "position": "Left Wing Back",
                        "from": "00:00:00.000",
                        "to": null,
                        "from_period": 1,
                        "to_period": null,
                        "start_reason": "Starting XI",
                        "end_reason": "Final Whistle"
                    }
                ],
                "stats": {
                    "own_goals": 0,
                    "goals": 1,
                    "assists": 3,
                    "penalties_scored": 0,
                    "penalties_missed": 0,
                    "penalties_saved": 0
                }
            },
            {
                "player_id": 29560,
                "player_name": "Juli\u00e1n \u00c1lvarez",
                "player_nickname": null,
                "birth_date": "2000-01-31",
                "player_gender": "male",
                "player_height": 170.0,
                "player_weight": 71.0,
                "jersey_number": 19,
                "country": {
                    "id": 11,
                    "name": "Argentina"
                },
                "positions": [
                    {
                        "position_id": 20,
                        "position": "Left Attacking Midfield",
                        "from": "00:00:00.000",
                        "to": "00:45:00.000",
                        "from_period": 1,
                        "to_period": 2,
                        "start_reason": "Starting XI",
                        "end_reason": "Tactical Shift"
                    },
                    {
                        "position_id": 23,
                        "position": "Center Forward",
                        "from": "00:45:00.000",
                        "to": "01:10:11.406",
                        "from_period": 2,
                        "to_period": 2,
                        "start_reason": "Tactical Shift",
                        "end_reason": "Substitution - Off (Tactical)",
                        "counterpart_id": 40874,
                        "counterpart_name": "Matheus Luiz Nunes"
                    }
                ],
                "stats": {
                    "own_goals": 0,
                    "goals": 0,
                    "assists": 0,
                    "penalties_scored": 0,
                    "penalties_missed": 0,
                    "penalties_saved": 0
                }
            },
            {
                "player_id": 33018,
                "player_name": "Jo\u0161ko Gvardiol",
                "player_nickname": null,
                "birth_date": "2002-01-23",
                "player_gender": "male",
                "player_height": 185.0,
                "player_weight": 80.0,
                "jersey_number": 24,
                "country": {
                    "id": 56,
                    "name": "Croatia"
                },
                "positions": [],
                "stats": []
            },
            {
                "player_id": 40874,
                "player_name": "Matheus Luiz Nunes",
                "player_nickname": "Matheus Nunes",
                "birth_date": "1998-08-27",
                "player_gender": "male",
                "player_height": 184.0,
                "player_weight": 78.0,
                "jersey_number": 27,
                "country": {
                    "id": 183,
                    "name": "Portugal"
                },
                "positions": [
                    {
                        "position_id": 20,
                        "position": "Left Attacking Midfield",
                        "from": "01:10:11.406",
                        "to": "01:24:36.000",
                        "from_period": 2,
                        "to_period": 2,
                        "start_reason": "Substitution - On (Tactical)",
                        "end_reason": "Tactical Shift",
                        "counterpart_id": 29560,
                        "counterpart_name": "Juli\u00e1n \u00c1lvarez"
                    },
                    {
                        "position_id": 23,
                        "position": "Center Forward",
                        "from": "01:24:36.000",
                        "to": null,
                        "from_period": 2,
                        "to_period": null,
                        "start_reason": "Tactical Shift",
                        "end_reason": "Final Whistle"
                    }
                ],
                "stats": {
                    "own_goals": 0,
                    "goals": 0,
                    "assists": 0,
                    "penalties_scored": 0,
                    "penalties_missed": 0,
                    "penalties_saved": 0
                }
            },
            {
                "player_id": 48705,
                "player_name": "Rico Lewis",
                "player_nickname": null,
                "birth_date": "2004-11-21",
                "player_gender": "male",
                "player_height": 169.0,
                "player_weight": null,
                "jersey_number": 82,
                "country": {
                    "id": 68,
                    "name": "England"
                },
                "positions": [
                    {
                        "position_id": 7,
                        "position": "Right Wing Back",
                        "from": "01:10:11.268",
                        "to": null,
                        "from_period": 2,
                        "to_period": null,
                        "start_reason": "Substitution - On (Tactical)",
                        "end_reason": "Final Whistle",
                        "counterpart_id": 3244,
                        "counterpart_name": "John Stones"
                    }
                ],
                "stats": {
                    "own_goals": 0,
                    "goals": 0,
                    "assists": 0,
                    "penalties_scored": 0,
                    "penalties_missed": 0,
                    "penalties_saved": 0
                }
            },
            {
                "player_id": 104825,
                "player_name": "Oscar Bobb",
                "player_nickname": null,
                "birth_date": "2003-07-12",
                "player_gender": "male",
                "player_height": 162.0,
                "player_weight": null,
                "jersey_number": 52,
                "country": {
                    "id": 171,
                    "name": "Norway"
                },
                "positions": [
                    {
                        "position_id": 20,
                        "position": "Left Attacking Midfield",
                        "from": "01:24:35.047",
                        "to": null,
                        "from_period": 2,
                        "to_period": null,
                        "start_reason": "Substitution - On (Tactical)",
                        "end_reason": "Final Whistle",
                        "counterpart_id": 3193,
                        "counterpart_name": "Bernardo Mota Veiga de Carvalho e Silva"
                    }
                ],
                "stats": {
                    "own_goals": 0,
                    "goals": 0,
                    "assists": 1,
                    "penalties_scored": 0,
                    "penalties_missed": 0,
                    "penalties_saved": 0
                }
            }
        ],
        "formations": [
            {
                "period": 1,
                "timestamp": "00:00:00.000",
                "reason": "Starting XI",
                "formation": 3421
            }
        ],
        "events": [
            {
                "period": 1,
                "timestamp": "00:00:00.000",
                "type": "Half Start"
            },
            {
                "player_id": 6765,
                "player_name": "Rodrigo Hern\u00e1ndez Cascante",
                "period": 1,
                "timestamp": "00:29:12.933",
                "type": "Ground Pass",
                "outcome": "Assist"
            },
            {
                "player_id": 23650,
                "player_name": "Jeremy Doku",
                "period": 1,
                "timestamp": "00:29:13.819",
                "type": "Shot",
                "outcome": "Goal"
            },
            {
                "player_id": 23650,
                "player_name": "Jeremy Doku",
                "period": 1,
                "timestamp": "00:32:36.190",
                "type": "Ground Pass",
                "outcome": "Assist"
            },
            {
                "player_id": 3193,
                "player_name": "Bernardo Mota Veiga de Carvalho e Silva",
                "period": 1,
                "timestamp": "00:32:37.016",
                "type": "Shot",
                "outcome": "Goal"
            },
            {
                "player_id": 5549,
                "player_name": "Manuel Obafemi Akanji",
                "period": 1,
                "timestamp": "00:36:46.927",
                "type": "Shot",
                "outcome": "Goal"
            },
            {
                "period": 1,
                "timestamp": "00:49:03.054",
                "type": "Half End"
            },
            {
                "period": 2,
                "timestamp": "00:45:00.000",
                "type": "Half Start"
            },
            {
                "player_id": 23650,
                "player_name": "Jeremy Doku",
                "period": 2,
                "timestamp": "01:03:12.091",
                "type": "Ground Pass",
                "outcome": "Assist"
            },
            {
                "player_id": 4354,
                "player_name": "Phil Foden",
                "period": 2,
                "timestamp": "01:03:13.936",
                "type": "Shot",
                "outcome": "Goal"
            },
            {
                "player_id": 23650,
                "player_name": "Jeremy Doku",
                "period": 2,
                "timestamp": "01:22:40.892",
                "type": "High Pass",
                "outcome": "Assist"
            },
            {
                "player_id": 3193,
                "player_name": "Bernardo Mota Veiga de Carvalho e Silva",
                "period": 2,
                "timestamp": "01:22:48.786",
                "type": "Shot",
                "outcome": "Goal"
            },
            {
                "player_id": 104825,
                "player_name": "Oscar Bobb",
                "period": 2,
                "timestamp": "01:27:46.763",
                "type": "Low Pass",
                "outcome": "Assist"
            },
            {
                "player_id": 3306,
                "player_name": "Nathan Ak\u00e9",
                "period": 2,
                "timestamp": "01:27:47.443",
                "type": "Shot",
                "outcome": "Goal"
            },
            {
                "period": 2,
                "timestamp": "01:37:19.494",
                "type": "Half End"
            }
        ]
    },
    {
        "team_id": 28,
        "team_name": "AFC Bournemouth",
        "lineup": [
            {
                "player_id": 3331,
                "player_name": "Philip Billing",
                "player_nickname": null,
                "birth_date": "1996-06-11",
                "player_gender": "male",
                "player_height": 193.0,
                "player_weight": 83.0,
                "jersey_number": 29,
                "country": {
                    "id": 61,
                    "name": "Denmark"
                },
                "positions": [
                    {
                        "position_id": 11,
                        "position": "Left Defensive Midfield",
                        "from": "00:00:00.000",
                        "to": "01:10:56.608",
                        "from_period": 1,
                        "to_period": 2,
                        "start_reason": "Starting XI",
                        "end_reason": "Substitution - Off (Tactical)",
                        "counterpart_id": 9286,
                        "counterpart_name": "Antoine Semenyo"
                    }
                ],
                "stats": {
                    "own_goals": 0,
                    "goals": 0,
                    "assists": 0,
                    "penalties_scored": 0,
                    "penalties_missed": 0,
                    "penalties_saved": 0
                }
            },
            {
                "player_id": 3614,
                "player_name": "Dominic Solanke",
                "player_nickname": null,
                "birth_date": "1997-09-14",
                "player_gender": "male",
                "player_height": 187.0,
                "player_weight": 80.0,
                "jersey_number": 9,
                "country": {
                    "id": 68,
                    "name": "England"
                },
                "positions": [
                    {
                        "position_id": 23,
                        "position": "Center Forward",
                        "from": "00:00:00.000",
                        "to": "01:24:25.641",
                        "from_period": 1,
                        "to_period": 2,
                        "start_reason": "Starting XI",
                        "end_reason": "Substitution - Off (Off Camera)",
                        "counterpart_id": 8063,
                        "counterpart_name": "Justin Kluivert"
                    }
                ],
                "stats": {
                    "own_goals": 0,
                    "goals": 0,
                    "assists": 0,
                    "penalties_scored": 0,
                    "penalties_missed": 0,
                    "penalties_saved": 0
                }
            },
            {
                "player_id": 4111,
                "player_name": "Marcus Tavernier",
                "player_nickname": null,
                "birth_date": "1999-03-22",
                "player_gender": "male",
                "player_height": 177.0,
                "player_weight": 70.0,
                "jersey_number": 16,
                "country": {
                    "id": 68,
                    "name": "England"
                },
                "positions": [
                    {
                        "position_id": 21,
                        "position": "Left Wing",
                        "from": "00:00:00.000",
                        "to": "01:11:10.290",
                        "from_period": 1,
                        "to_period": 2,
                        "start_reason": "Starting XI",
                        "end_reason": "Substitution - Off (Tactical)",
                        "counterpart_id": 16184,
                        "counterpart_name": "Luis Fernando Sinisterra Lucum\u00ed"
                    }
                ],
                "stats": {
                    "own_goals": 0,
                    "goals": 0,
                    "assists": 0,
                    "penalties_scored": 0,
                    "penalties_missed": 0,
                    "penalties_saved": 0
                }
            },
            {
                "player_id": 4143,
                "player_name": "Joe Rothwell",
                "player_nickname": null,
                "birth_date": "1995-01-11",
                "player_gender": "male",
                "player_height": 185.0,
                "player_weight": 77.0,
                "jersey_number": 8,
                "country": {
                    "id": 68,
                    "name": "England"
                },
                "positions": [
                    {
                        "position_id": 9,
                        "position": "Right Defensive Midfield",
                        "from": "00:43:33.946",
                        "to": null,
                        "from_period": 1,
                        "to_period": null,
                        "start_reason": "Substitution - On (Injury)",
                        "end_reason": "Final Whistle",
                        "counterpart_id": 91951,
                        "counterpart_name": "Alex Scott"
                    }
                ],
                "stats": {
                    "own_goals": 0,
                    "goals": 0,
                    "assists": 0,
                    "penalties_scored": 0,
                    "penalties_missed": 0,
                    "penalties_saved": 0
                }
            },
            {
                "player_id": 4567,
                "player_name": "David Brooks",
                "player_nickname": null,
                "birth_date": "1997-07-08",
                "player_gender": "male",
                "player_height": 173.0,
                "player_weight": 62.0,
                "jersey_number": 7,
                "country": {
                    "id": 249,
                    "name": "Wales"
                },
                "positions": [],
                "stats": []
            },
            {
                "player_id": 4767,
                "player_name": "Chris Mepham",
                "player_nickname": null,
                "birth_date": "1997-11-05",
                "player_gender": "male",
                "player_height": 193.0,
                "player_weight": 88.0,
                "jersey_number": 6,
                "country": {
                    "id": 249,
                    "name": "Wales"
                },
                "positions": [
                    {
                        "position_id": 3,
                        "position": "Right Center Back",
                        "from": "00:00:00.000",
                        "to": "00:45:00.000",
                        "from_period": 1,
                        "to_period": 2,
                        "start_reason": "Starting XI",
                        "end_reason": "Substitution - Off (Tactical)",
                        "counterpart_id": 27773,
                        "counterpart_name": "Marcos Senesi"
                    }
                ],
                "stats": {
                    "own_goals": 0,
                    "goals": 0,
                    "assists": 0,
                    "penalties_scored": 0,
                    "penalties_missed": 0,
                    "penalties_saved": 0
                }
            },
            {
                "player_id": 6409,
                "player_name": "Adam Smith",
                "player_nickname": null,
                "birth_date": "1991-04-29",
                "player_gender": "male",
                "player_height": 180.0,
                "player_weight": 78.0,
                "jersey_number": 15,
                "country": {
                    "id": 68,
                    "name": "England"
                },
                "positions": [],
                "stats": []
            },
            {
                "player_id": 8063,
                "player_name": "Justin Kluivert",
                "player_nickname": null,
                "birth_date": "1999-05-05",
                "player_gender": "male",
                "player_height": 171.0,
                "player_weight": 67.0,
                "jersey_number": 19,
                "country": {
                    "id": 160,
                    "name": "Netherlands"
                },
                "positions": [
                    {
                        "position_id": 23,
                        "position": "Center Forward",
                        "from": "01:24:25.641",
                        "to": null,
                        "from_period": 2,
                        "to_period": null,
                        "start_reason": "Substitution - On (Off Camera)",
                        "end_reason": "Final Whistle",
                        "counterpart_id": 3614,
                        "counterpart_name": "Dominic Solanke"
                    }
                ],
                "stats": {
                    "own_goals": 0,
                    "goals": 0,
                    "assists": 0,
                    "penalties_scored": 0,
                    "penalties_missed": 0,
                    "penalties_saved": 0
                }
            },
            {
                "player_id": 9286,
                "player_name": "Antoine Semenyo",
                "player_nickname": null,
                "birth_date": "2000-01-07",
                "player_gender": "male",
                "player_height": 185.0,
                "player_weight": 79.0,
                "jersey_number": 24,
                "country": {
                    "id": 86,
                    "name": "Ghana"
                },
                "positions": [
                    {
                        "position_id": 11,
                        "position": "Left Defensive Midfield",
                        "from": "01:10:56.608",
                        "to": "01:11:18.150",
                        "from_period": 2,
                        "to_period": 2,
                        "start_reason": "Substitution - On (Tactical)",
                        "end_reason": "Tactical Shift",
                        "counterpart_id": 3331,
                        "counterpart_name": "Philip Billing"
                    },
                    {
                        "position_id": 17,
                        "position": "Right Wing",
                        "from": "01:11:18.150",
                        "to": null,
                        "from_period": 2,
                        "to_period": null,
                        "start_reason": "Tactical Shift",
                        "end_reason": "Final Whistle"
                    }
                ],
                "stats": {
                    "own_goals": 0,
                    "goals": 0,
                    "assists": 0,
                    "penalties_scored": 0,
                    "penalties_missed": 0,
                    "penalties_saved": 0
                }
            },
            {
                "player_id": 9938,
                "player_name": "Lloyd Kelly",
                "player_nickname": null,
                "birth_date": "1998-10-06",
                "player_gender": "male",
                "player_height": 190.0,
                "player_weight": 70.0,
                "jersey_number": 5,
                "country": {
                    "id": 68,
                    "name": "England"
                },
                "positions": [
                    {
                        "position_id": 5,
                        "position": "Left Center Back",
                        "from": "00:00:00.000",
                        "to": "00:45:00.000",
                        "from_period": 1,
                        "to_period": 2,
                        "start_reason": "Starting XI",
                        "end_reason": "Tactical Shift"
                    },
                    {
                        "position_id": 4,
                        "position": "Center Back",
                        "from": "00:45:00.000",
                        "to": null,
                        "from_period": 2,
                        "to_period": null,
                        "start_reason": "Tactical Shift",
                        "end_reason": "Final Whistle"
                    }
                ],
                "stats": {
                    "own_goals": 0,
                    "goals": 0,
                    "assists": 0,
                    "penalties_scored": 0,
                    "penalties_missed": 0,
                    "penalties_saved": 0
                }
            },
            {
                "player_id": 12510,
                "player_name": "Ryan Christie",
                "player_nickname": null,
                "birth_date": "1995-02-22",
                "player_gender": "male",
                "player_height": 178.0,
                "player_weight": 79.0,
                "jersey_number": 10,
                "country": {
                    "id": 201,
                    "name": "Scotland"
                },
                "positions": [
                    {
                        "position_id": 17,
                        "position": "Right Wing",
                        "from": "00:00:00.000",
                        "to": "01:11:18.150",
                        "from_period": 1,
                        "to_period": 2,
                        "start_reason": "Starting XI",
                        "end_reason": "Tactical Shift"
                    },
                    {
                        "position_id": 11,
                        "position": "Left Defensive Midfield",
                        "from": "01:11:18.150",
                        "to": null,
                        "from_period": 2,
                        "to_period": null,
                        "start_reason": "Tactical Shift",
                        "end_reason": "Final Whistle"
                    }
                ],
                "stats": {
                    "own_goals": 0,
                    "goals": 0,
                    "assists": 0,
                    "penalties_scored": 0,
                    "penalties_missed": 0,
                    "penalties_saved": 0
                }
            },
            {
                "player_id": 16184,
                "player_name": "Luis Fernando Sinisterra Lucum\u00ed",
                "player_nickname": "Luis Sinisterra",
                "birth_date": "1999-06-17",
                "player_gender": "male",
                "player_height": 172.0,
                "player_weight": 60.0,
                "jersey_number": 17,
                "country": {
                    "id": 49,
                    "name": "Colombia"
                },
                "positions": [
                    {
                        "position_id": 21,
                        "position": "Left Wing",
                        "from": "01:11:10.290",
                        "to": null,
                        "from_period": 2,
                        "to_period": null,
                        "start_reason": "Substitution - On (Tactical)",
                        "end_reason": "Final Whistle",
                        "counterpart_id": 4111,
                        "counterpart_name": "Marcus Tavernier"
                    }
                ],
                "stats": {
                    "own_goals": 0,
                    "goals": 1,
                    "assists": 0,
                    "penalties_scored": 0,
                    "penalties_missed": 0,
                    "penalties_saved": 0
                }
            },
            {
                "player_id": 16689,
                "player_name": "Maximillian James Aarons",
                "player_nickname": "Max Aarons",
                "birth_date": "2000-01-04",
                "player_gender": "male",
                "player_height": 170.0,
                "player_weight": 69.0,
                "jersey_number": 37,
                "country": {
                    "id": 68,
                    "name": "England"
                },
                "positions": [
                    {
                        "position_id": 7,
                        "position": "Right Wing Back",
                        "from": "00:00:00.000",
                        "to": null,
                        "from_period": 1,
                        "to_period": null,
                        "start_reason": "Starting XI",
                        "end_reason": "Final Whistle"
                    }
                ],
                "stats": {
                    "own_goals": 0,
                    "goals": 0,
                    "assists": 1,
                    "penalties_scored": 0,
                    "penalties_missed": 0,
                    "penalties_saved": 0
                }
            },
            {
                "player_id": 18237,
                "player_name": "Ionu\u021b Andrei Radu",
                "player_nickname": "Ionut Radu",
                "birth_date": "1997-05-28",
                "player_gender": "male",
                "player_height": 188.0,
                "player_weight": 70.0,
                "jersey_number": 20,
                "country": {
                    "id": 187,
                    "name": "Romania"
                },
                "positions": [
                    {
                        "position_id": 1,
                        "position": "Goalkeeper",
                        "from": "00:00:00.000",
                        "to": null,
                        "from_period": 1,
                        "to_period": null,
                        "start_reason": "Starting XI",
                        "end_reason": "Final Whistle"
                    }
                ],
                "stats": {
                    "own_goals": 0,
                    "goals": 0,
                    "assists": 0,
                    "penalties_scored": 0,
                    "penalties_missed": 0,
                    "penalties_saved": 0
                }
            },
            {
                "player_id": 24937,
                "player_name": "Mark Travers",
                "player_nickname": null,
                "birth_date": "1999-05-18",
                "player_gender": "male",
                "player_height": 191.0,
                "player_weight": 82.0,
                "jersey_number": 42,
                "country": {
                    "id": 109,
                    "name": "Ireland"
                },
                "positions": [],
                "stats": []
            },
            {
                "player_id": 27773,
                "player_name": "Marcos Senesi",
                "player_nickname": null,
                "birth_date": "1997-05-10",
                "player_gender": "male",
                "player_height": 185.0,
                "player_weight": 80.0,
                "jersey_number": 25,
                "country": {
                    "id": 11,
                    "name": "Argentina"
                },
                "positions": [
                    {
                        "position_id": 5,
                        "position": "Left Center Back",
                        "from": "00:45:00.000",
                        "to": null,
                        "from_period": 2,
                        "to_period": null,
                        "start_reason": "Substitution - On (Tactical)",
                        "end_reason": "Final Whistle",
                        "counterpart_id": 4767,
                        "counterpart_name": "Chris Mepham"
                    }
                ],
                "stats": {
                    "own_goals": 0,
                    "goals": 0,
                    "assists": 0,
                    "penalties_scored": 0,
                    "penalties_missed": 0,
                    "penalties_saved": 0
                }
            },
            {
                "player_id": 39136,
                "player_name": "Illia Zabarnyi",
                "player_nickname": "Ilya Zabarnyi",
                "birth_date": "2002-09-01",
                "player_gender": "male",
                "player_height": 189.0,
                "player_weight": 80.0,
                "jersey_number": 27,
                "country": {
                    "id": 238,
                    "name": "Ukraine"
                },
                "positions": [
                    {
                        "position_id": 4,
                        "position": "Center Back",
                        "from": "00:00:00.000",
                        "to": "00:45:00.000",
                        "from_period": 1,
                        "to_period": 2,
                        "start_reason": "Starting XI",
                        "end_reason": "Tactical Shift"
                    },
                    {
                        "position_id": 3,
                        "position": "Right Center Back",
                        "from": "00:45:00.000",
                        "to": null,
                        "from_period": 2,
                        "to_period": null,
                        "start_reason": "Tactical Shift",
                        "end_reason": "Final Whistle"
                    }
                ],
                "stats": {
                    "own_goals": 0,
                    "goals": 0,
                    "assists": 0,
                    "penalties_scored": 0,
                    "penalties_missed": 0,
                    "penalties_saved": 0
                }
            },
            {
                "player_id": 89635,
                "player_name": "Milos Kerkez",
                "player_nickname": null,
                "birth_date": "2003-11-07",
                "player_gender": "male",
                "player_height": 176.0,
                "player_weight": 71.0,
                "jersey_number": 3,
                "country": {
                    "id": 103,
                    "name": "Hungary"
                },
                "positions": [
                    {
                        "position_id": 8,
                        "position": "Left Wing Back",
                        "from": "00:00:00.000",
                        "to": null,
                        "from_period": 1,
                        "to_period": null,
                        "start_reason": "Starting XI",
                        "end_reason": "Final Whistle"
                    }
                ],
                "stats": {
                    "own_goals": 0,
                    "goals": 0,
                    "assists": 0,
                    "penalties_scored": 0,
                    "penalties_missed": 0,
                    "penalties_saved": 0
                }
            },
            {
                "player_id": 91951,
                "player_name": "Alex Scott",
                "player_nickname": null,
                "birth_date": "2003-08-21",
                "player_gender": "male",
                "player_height": 178.0,
                "player_weight": null,
                "jersey_number": 14,
                "country": {
                    "id": 68,
                    "name": "England"
                },
                "positions": [
                    {
                        "position_id": 9,
                        "position": "Right Defensive Midfield",
                        "from": "00:00:00.000",
                        "to": "00:42:32.587",
                        "from_period": 1,
                        "to_period": 1,
                        "start_reason": "Starting XI",
                        "end_reason": "Player Off"
                    },
                    {
                        "position_id": 9,
                        "position": "Right Defensive Midfield",
                        "from": "00:43:32.510",
                        "to": "00:43:33.946",
                        "from_period": 1,
                        "to_period": 1,
                        "start_reason": "Player On",
                        "end_reason": "Substitution - Off (Injury)",
                        "counterpart_id": 4143,
                        "counterpart_name": "Joe Rothwell"
                    }
                ],
                "stats": {
                    "own_goals": 0,
                    "goals": 0,
                    "assists": 0,
                    "penalties_scored": 0,
                    "penalties_missed": 0,
                    "penalties_saved": 0
                }
            },
            {
                "player_id": 95042,
                "player_name": "Dango Aboubacar Faissal Ouattara",
                "player_nickname": "Dango Ouattara",
                "birth_date": "2002-02-11",
                "player_gender": "male",
                "player_height": 177.0,
                "player_weight": 71.0,
                "jersey_number": 11,
                "country": {
                    "id": 36,
                    "name": "Burkina Faso"
                },
                "positions": [],
                "stats": []
            }
        ],
        "formations": [
            {
                "period": 1,
                "timestamp": "00:00:00.000",
                "reason": "Starting XI",
                "formation": 343
            }
        ],
        "events": [
            {
                "period": 1,
                "timestamp": "00:00:00.000",
                "type": "Half Start"
            },
            {
                "player_id": 3331,
                "player_name": "Philip Billing",
                "period": 1,
                "timestamp": "00:31:10.715",
                "type": "Bad Behaviour",
                "outcome": "Yellow Card"
            },
            {
                "period": 1,
                "timestamp": "00:49:03.054",
                "type": "Half End"
            },
            {
                "period": 2,
                "timestamp": "00:45:00.000",
                "type": "Half Start"
            },
            {
                "player_id": 16689,
                "player_name": "Maximillian James Aarons",
                "period": 2,
                "timestamp": "01:13:42.397",
                "type": "Ground Pass",
                "outcome": "Assist"
            },
            {
                "player_id": 16184,
                "player_name": "Luis Fernando Sinisterra Lucum\u00ed",
                "period": 2,
                "timestamp": "01:13:45.165",
                "type": "Shot",
                "outcome": "Goal"
            },
            {
                "period": 2,
                "timestamp": "01:37:19.494",
                "type": "Half End"
            }
        ]
    }
]